[
  {
    "title": "সোনালিকা DI 60 RX ট্রাক্টর",
    "category": "Vehicle",
    "price": "১৩০০০০০",
    "des": " DI-60 RX ইঞ্জিন মেক ইন্টারন্যাশনাল ট্র্যাক্টর লিমিটেড এইচপি ক্যাটাগরি 60 এইচপি ক্যাটাগরি নং সিলিন্ডার 4 রেটেড আরপিএম 2200 এয়ারক্লিনার অয়েল বাথ উইথ প্রি ক্লিনার ট্রান্সমিশন ক্লাচ ডুয়াল ক্লাচ ট্রান্সমিশন টাইপ কনস্ট্যান্টমেশ নং গিয়ারস 8F+2R PTO PTO হাইড্রাক্স (540 Option) লিফ্ট ক্যাপাসিটি 2000 কেজি ব্রেক OIB স্টিয়ারিং মেকানিক্যাল (Optnl- PS) ফুয়েল ট্যাঙ্ক ক্যাপাসিটি 65 Ltr ফ্রন্ট টায়ার 7.5 x 16 পিছনের টায়ার 16.9 x 28.",
    "picture": "https://www.banglastall.com/pho_1/1486541458.jpg"
  },
  {
    "title": "সোনালিকা DI 50 Rx হাই পারফরমেন্স ট্রাক্টর",
    "category": "Vehicle",
    "price": "৳ ১১,৮০,০০০",
    "des": " টেকনিক্যাল স্পেসিফিকেশন স্ট্যান্ডার্ড ফিচারস DI-50 RX 2WD/4WD ইঞ্জিন ইঞ্জিন টাইপ 3102 IL বিনা কোল্ডস্টার্ট এইচপি ক্যাটাগরি 50 সিলিন্ডারের সংখ্যা 3 অ্যাসপিরেশন ন্যাচারাল অ্যাসপিরেশন বোর/স্ট্রোক(মিমি) 102/118 কিউবিক ক্যাপাসিটি (3আরপি 9+আরপিটেড) 25mm) 2100 এয়ার ক্লিনার ক্লগিং সেন্সর সহ ড্রাই এয়ার ক্লিনার ম্যাক্স টর্ক (Nm) @ RPM 190(+/-5%)@1200 RPM(+/-100) ট্রান্সমিশন ড্রাইভ 2wd/4wd ক্লাচ ডুয়াল ক্লাচ গিয়ারবক্স 8F+2R ট্রান্সমিশন কনস PTO PTO (rpm) 540 rpm PTO (অ্যাকচুয়েশন) যান্ত্রিক, হাতে চালিত ডিফ লক ডিফ।",
    "picture": "https://www.millat.com.pk/wp-content/uploads/2021/06/240.png"
  },
  {
    "title": "সোনালিকা ডিআই 750 II ট্রাক্টর",
    "category": "Vehicle",
    "price": "৳ ১১,২০,০০০",
    "des": " বিশেষ বৈশিষ্ট্য 01. ভাল টান ক্ষমতা 02. উচ্চ জ্বালানী সাশ্রয়ী 03. উচ্চতর ব্যাকআপ টর্ক 04. ফুয়েল গেজ 05. ভাল পারফরম্যান্স ওভার টার্নিং (অল্প RPM ড্রপ) 06. ইউরো II ইঞ্জিন স্পেসিফিকেশন 01. ইঞ্জিন মডেল 3102FL 02. HP ক্যাটাগরি 053 টাইপ 4 স্ট্রোক, ডাইরেক্ট ইনজেকশন ডিজেল ইঞ্জিন, ন্যাচারাল অ্যাসপিরেশন 04. সিলিন্ডারের সংখ্যা 03 05. কুলিং সিস্টেম ওয়াটার কুলড 06. ট্রেলার, সিঙ্গেল অ্যাক্সি (টন) 5 07. ইউটিলিটি কাল্টিভেশন 08. ফুয়েল ট্যাঙ্ক 55 লিটার 02 লিটার কেজি 10. ওজন 2020 কেজি 11. গ্রাউন্ড ক্লিয়ারেন্স 42.5 সেমি",
    "picture": "https://www.banglastall.com/pho_1/1486540951.jpg"
  },
  {
    "name": "সোনালিকা DI 745 Rx ট্রাক্টর",
    "category": "Vehicle",
    "price": "৳ ১০,২০,০০০",
    "des": " ইঞ্জিন মেক ইন্টারন্যাশনাল ট্র্যাক্টর লিমিটেড এইচপি ক্যাটাগরি 50 এইচপি ক্যাটাগরি নম্বর সিলিন্ডারের 3 রেটেড rpm 2100 এয়ারক্লিনার অয়েল বাথ উইথ প্রি ক্লিনার ট্রান্সমিশন ক্লাচ ডুয়াল ক্লাচ (Optnl- সিঙ্গেল ক্লাচ) ট্রান্সমিশন টাইপ কনস্ট্যান্টমেশ নং গিয়ারস 8F+2R50 লিমিক্স 2R50 লিমিক্স কেজি ব্রেক OIB (Optnl- ড্রাই ডিস্ক ব্রেক) স্টিয়ারিং মেকানিক্যাল (Optnl- PS) ফুয়েল ট্যাঙ্ক ক্যাপাসিটি 55 Ltr ফ্রন্ট টায়ার 6.0x16 রিয়ার টায়ার 14.9 x 28 (Optnl - 13.6x28)",
    "picture": "https://www.banglastall.com/pho_1/1486540731.jpg"
  },
  {
    "name": "সোনালিকা ডিআই 745 ট্রাক্টর",
    "category": "Vehicle",
    "price": "৳ ১০,৫৫,০০০",
    "des": " বিশেষ বৈশিষ্ট্য 01. ভাল টানা শক্তি 02. উচ্চ জ্বালানী সাশ্রয়ী 03. উচ্চতর ব্যাকআপ টর্ক 04. ফুয়েল গেজ 05. টার্নিং ওভার ভাল পারফরম্যান্স (অল্প RPM ড্রপ) 06. ইউরো III ইঞ্জিন স্পেসিফিকেশন 01. ইঞ্জিন মডেল 3100FL 02. HP Categ53 টাইপ 4 স্ট্রোক, ডাইরেক্ট ইনজেকশন ডিজেল ইঞ্জিন, ন্যাচারাল অ্যাসপিরেশন 04. সিলিন্ডারের সংখ্যা 03 05. কুলিং সিস্টেম ওয়াটার কুলড 06. ট্রেলার, সিঙ্গেল অ্যাক্সি (টন) 5 07. ইউটিলিটি বহন, চাষাবাদ 08. জ্বালানী ট্যাঙ্ক 09. ক্ষমতা 1200 কেজি 10. ওজন 1860 কেজি 11. গ্রাউন্ড ক্লিয়ারেন্স 42.5 সেমি/16.73 ইঞ্চি",
    "picture": "https://www.banglastall.com/pho_1/1486539106.jpg"
  },
  {
    "name": "সোনালিকা আরএক্স ৩৫ ট্রাক্টর",
    "category": "Vehicle",
    "price": "৳ ৯,২০,০০০",
    "des": "-এইচ.পি. 39 - টায়ারের আকার- 13.6.28 - সাধারণ স্টিয়ারিং - ডিস্ক ব্রেক - ড্রাই টাইপ এয়ার ফিল্টার",
    "picture": "https://www.banglastall.com/pho_1/1486538911.jpg"
  },
  {
    "title": "রিডোমিল গোল্ড ছত্রাকনাশক",
    "category": "Insecticides",
    "price": "৳ ১৫০",
    "des": "রিডোমিল গোল্ড ছত্রাকনাশক হল ম্যানকোজেব এবং মেফেনক্সামের সংমিশ্রণ। এই সংমিশ্রণটি ছত্রাক এবং অন্যান্য ছত্রাকের রোগজীবাণু নিয়ন্ত্রণ করে যা কুমড়া, তরমুজ, বোতল, শসা, স্কোয়াশ, আলু, বিট, পেঁয়াজ, টমেটো এবং অ্যাডেনিয়ামকে প্রভাবিত করে। বাংলাদেশে রিডোমিল গোল্ডের 100 গ্রাম প্যাকের দাম মাত্র 150 টাকা। ",
    "picture": "https://www.garden.com.bd/1736-medium_default/ridomil-gold-fungicide.jpg"
  },
  {
    "title": "টক্সিমাইট (অ্যাবামেকটিন 1.8 ইসি)",
    "category": "Insecticides",
    "price": "৳ ১৩০",
    "des": "Abamectin 1.8 EC ব্যাপকভাবে মাইট, বিভিন্ন পোকামাকড় এবং অন্যান্য ধ্বংসাত্মক জীব নিয়ন্ত্রণে ব্যবহৃত হয়। মাইট দ্বারা আক্রান্ত কোঁকড়া পাতার জন্য টক্সিমাইট খুবই সহনীয়",
    "picture": "https://www.garden.com.bd/1694-home_default/toximite-abamectin-18-ec.jpg"
  },
  {
    "title": "বুস্টআপ (সুপার স্প্রেডার)",
    "category": "Insecticides",
    "price": "৳ ৪০",
    "des": " বুস্টআপ হল একটি সিলিকন-ভিত্তিক সার্ফ্যাক্ট্যান্ট এবং সুপার স্প্রেডার, এটি কীটনাশক, পিজিআর এবং সারের সাথে মিশ্রিত হলে এটি দ্রুত কাজ করে।",
    "picture": "https://www.garden.com.bd/1640-medium_default/boostup.jpg"
  },
  {
    "title": "রাগবি 10G - 1kg প্যাক",
    "category": "Insecticides",
    "price": "৳ ৬৬০",
    "des": "রাগবি 10G হল গাছের নেমাটোড নিয়ন্ত্রণের জন্য একটি বিস্তৃত বর্ণালী গ্রানুল কন্টাক্ট নেমাটিসাইড। এফএমসি কর্পোরেশন ইউএসএ দ্বারা প্রণয়ন করা এবং বাংলাদেশে NAAFCO দ্বারা একচেটিয়াভাবে বাজারজাত করা, রাগবি 10G এর উচ্চ কার্যকারিতা, দীর্ঘ অবশিষ্ট সময় এবং নন-সিস্টেমিক অ্যাকশন রয়েছে (এটি ফলের অবশিষ্টাংশ ফেলে না), যার ফলে শিকড়গুলি সুস্থ থাকে এবং আরও ভাল শোষণ করতে পারে। জল এবং পুষ্টির। ",
    "picture": "https://www.garden.com.bd/1637-medium_default/rugby-10g.jpg"
  },
  {
    "title": "টুন্ড্রা 20 এসপি (অ্যাসেটামিপ্রিড)",
    "category": "Insecticides",
    "price": "৳ ৩৯",
    "des": " Tundra (Acetamiprid 20 SP) হল একটি দ্রবণীয় পাউডার যা Acetamiprid-এর সক্রিয় উপাদানের 20% ধারণ করে। তুন্দ্রা তুলা এবং মটরশুটি ফসলে এফিড, জাসিড এবং সাদা মাছি নিয়ন্ত্রণের জন্য একটি অত্যন্ত কার্যকর পদ্ধতিগত কীটনাশক।",
    "picture": "https://www.garden.com.bd/1562-medium_default/tundra-20-sp-acetamiprid.jpg"
  },
  {
    "title": "Hadiavit 80 WDG সালফার (৮০% সালফার)",
    "category": "Insecticides",
    "price": "৳ ৫০ ",
    "des": "Hadiavit 80 WDG-এ 80% সালফার (৮০% সালফার) রয়েছে যা সমস্ত ফসলের জন্য একটি ম্যাক্রোনিউট্রিয়েন্ট। মোট ধানের প্রায় ৬০% উপরিভাগে সালফারের ঘাটতি রয়েছে। যদিও Hadiavit 80 WDG Cucurbit, Tea & Jute-এ নিবন্ধিত, বাংলাদেশের সারা দেশে কৃষকরা সালফারের ঘাটতিযুক্ত মাটির জন্য ছত্রাকনাশক, মাইটিসাইডের পাশাপাশি সালফারের উত্স হিসাবে পণ্যটি ব্যবহার করে। এটি মাইট পোকা নিয়ন্ত্রণ করতেও ব্যবহৃত হয় ",
    "picture": "https://www.garden.com.bd/1754-medium_default/hadiavit-sulphur.jpg"
  },
  {
    "title": " হিউমিস্টার ডাব্লুজি - উদ্ভিদের জন্য হিউমিক অ্যাসিড ",
    "category": "Fertilizer",
    "price": "৳ ৩৪৫",
    "des": " হিউমিস্টার উদ্ভিদের জন্য হিউমিক অ্যাসিড সরবরাহ করে। প্রতিটি প্যাকে রয়েছে - হিউমিক অ্যাসিড - 75%, ফলভিক - 12% এবং পটাসিয়াম - 18%। হিউমিস্টার মাটির পুষ্টিগুণ বৃদ্ধি করে যাতে উদ্ভিদকে গ্রহণের জন্য প্রস্তুত করে, উপলব্ধ উপকারী অণুজীবকে সক্রিয় করে এবং রাসায়নিক সারের কার্যকারিতা বাড়ায়।",
    "picture": "https://www.garden.com.bd/1788-medium_default/humic-acid.jpg"
  },
  {
    "title": "পাতা ছাঁচ কম্পোস্ট ",
    "category": "Fertilizer",
    "price": "৳ ৫০",
    "des": " পাতার ছাঁচ একটি পাত্র, মাটি কন্ডিশনার, বা মিশ্রণ এবং বীজ অঙ্কুরোদগম কম্পোস্টে মালচ হিসাবে ব্যবহার করা যেতে পারে। লিচুর পাতা দিয়ে আমাদের লিফ মোল্ড কম্পোস্ট তৈরি করা হয়। পাতার ছাঁচ ক্যাকটাস, অ্যাডেনিয়াম এবং সুকুলেন্টের পাশাপাশি সবজি, ফল এবং অন্যান্য ফুলের গাছের জন্য আদর্শ।",
    "picture": "https://www.garden.com.bd/1775-medium_default/leaf-mold-compost.jpg"
  },
  {
    "title": " ব্লুমিং বুস্টার NPK (10-52-10) ",
    "category": "Fertilizer",
    "price": "৳ ৩০০",
    "des": "এই পানিতে দ্রবণীয় ব্লুমিং বুস্টার NPK (10-52-10) আপনার গাছে ফুল ফোটানোর জন্য ডিজাইন করা হয়েছে। প্রতি লিটারে 2 গ্রাম ফলিয়ার খাওয়ানো হিসাবে প্রয়োগ করুন বা জল দিয়ে মাটিতে প্রয়োগ করা যেতে পারে। প্যাকে 100 গ্রাম NPK রয়েছে।",
    "picture": "https://www.garden.com.bd/1759-medium_default/blooming-booster-npk.jpg"
  },
  {
    "title": " জেনিম্যাক্স (গিবেরেলিক অ্যাসিড ট্যাবলেট) ",
    "category": "Fertilizer",
    "price": "৳ ১৭৫",
    "des": " জিবেরেলিক অ্যাসিড (GA3) হল একটি হরমোন যা উদ্ভিদ এবং বিভিন্ন ছত্রাকের মধ্যে পাওয়া যায়। স্বাভাবিক অবস্থায় গাছপালা প্রচুর পরিমাণে জিবেরেলিক অ্যাসিড তৈরি করে। কোম্পানিগুলি উদ্ভিদ এবং ছত্রাক থেকে সংগৃহীত অণুজীব ব্যবহার করে শিল্পভাবে এই হরমোন তৈরি করছে। জেনিম্যাক্স গ্রোথ হরমোন ট্যাবলেটটি ফুল ও ফলের পরিবর্তন বা বিকাশের জন্য ব্যবহার করা হয়, এছাড়াও এটি প্রকোপ হ্রাস করবে।",
    "picture": "https://www.garden.com.bd/1693-medium_default/gibberellic-acid-tablet.jpg"
  },
  {
    "title": " বুস্টআপ (সুপার স্প্রেডার) ",
    "category": "Fertilizer",
    "price": "৳ ৪০",
    "des": "বুস্টআপ হল একটি সিলিকন-ভিত্তিক সার্ফ্যাক্ট্যান্ট এবং সুপার স্প্রেডার, এটি কীটনাশক, পিজিআর এবং সারের সাথে মিশ্রিত হলে এটি দ্রুত কাজ করে। ",
    "picture": "https://www.garden.com.bd/1640-medium_default/boostup.jpg"
  },
  {
    "title": " লিব্রেল জিঙ্ক (চেলেটেড জিঙ্ক সার) ",
    "category": "Fertilizer",
    "price": "৳ ৯৩",
    "des": " দস্তা গাছের স্বাস্থ্য এবং বৃদ্ধির জন্য একটি অত্যাবশ্যক মাইক্রোনিউট্রিয়েন্ট। জিঙ্ক সার সাধারণত দুটি আকারে আসে: চেলেটেড জিঙ্ক এবং জিঙ্ক সালফেট। যেহেতু চেলেটেড জিঙ্ক উদ্ভিদের শোষণ করা সহজ, এটি নিয়মিত জিঙ্কের চেয়ে দ্রুত দস্তার ঘাটতি পূরণ করবে। চেলেটেড জিঙ্ক সার অন্যান্য সার এবং পুষ্টির সাথে একত্রিত করা যেতে পারে এবং ঘাটতি দেখা দেওয়ার আগে নিয়মিত খাওয়ানোর সময়সূচীর জন্য এটি আদর্শ। চেলেটেড জিঙ্ক অত্যন্ত কার্যকরী যার ফলে উচ্চ ফলন হয়। এই সার চারা থেকে মাঝামাঝি ঋতু প্রয়োগ পর্যন্ত ব্যবহার করা যেতে পারে যা সেচ বা ফলিয়ার স্প্রে দিয়ে করা যেতে পারে",
    "picture": "https://www.garden.com.bd/1405-medium_default/chelated-zinc-fertilizer.jpg"
  },
  {
    "title": " আরএফএল ওয়াটার পাম্প সেন্ট্রিফুগাল ",
    "category": "WaterPump",
    "price": "৳ ৫৭৯৯",
    "des": "আরএফএল ওয়াটার পাম্প সেন্ট্রিফুগাল  আইটেম কোড ৮০৩২১ ব্র্যান্ড আরএফএল ওয়াটার পাম্প ২য় তলা পর্যন্ত ঘরোয়া ব্যবহার",
    "picture": "https://images.othoba.com/images/thumbs/0346577_rfl-water-pump-centrifugal-1x1-05hp-rcm-130.jpeg"
  },
  {
    "title": "আরএফএল ওয়াটার পাম্প জেট ",
    "category": "WaterPump",
    "price": "৳ ৭৭৬৬",
    "des": "আরএফএল ওয়াটার পাম্প জেট আইটেম কোড: ৮৫০০২ ব্র্যান্ড: আরএফএল ওয়াটার পাম্প ৪র্থ তলা পর্যন্ত ঘরোয়া ব্যবহার",
    "picture": "https://images.othoba.com/images/thumbs/0346572_rfl-water-pump-jet-1x1-1hp-rsjm10m.jpeg"
  },
  {
    "title": " আরএফএল সাবমারসিবল পাম্প ",
    "category": "WaterPump",
    "price": "৳ ৬৭,৩২০",
    "des": "আরএফএল সাবমারসিবল পাম্প (এইচডি) ৬ আইটেম কোড: ৮৬৮৬০৪ এসপি: ৭.৫ কিলোওয়াট: ৫.৬ হেড/মি: ১১-২৯-৪১ প্রবাহ/এলএমপি: ১৩০০-৮০০-৩০০ ভাল আকার: ৬ রঙ: সিলভার এবং কালো (প্রদত্ত ছবি হিসাবে)।",
    "picture": "https://images.othoba.com/images/thumbs/0372729_rfl-submersible-pump-hd-6.jpeg"
  },
  {
    "title": " THF-5AX গাজী সেচ  ",
    "category": "WaterPump",
    "price": "৳ ১২,৯৬৮",
    "des": "কর্মক্ষমতা: মিনিট ( হেড 9-24) (ক্ষমতা লিটার (530-80) পাম্প সাইড: অতিরিক্ত সলিড কাস্ট আয়রন পাম্প বডি এবং ব্র্যাকেট। ব্র্যাশ ইমপেলার স্টেইনলেস স্টীল খাদ, উচ্চ-মানের যান্ত্রিক সীল। মান নিয়ন্ত্রণ: আমাদের সমস্ত পাম্প UNI 6871-71P ক্যাট অল স্ট্যান্ডার্স অনুসারে পৃথকভাবে ফ্যাক্টরি পরীক্ষা করা হয়।",
    "picture": "https://images.othoba.com/images/thumbs/0487373_thf-5ax-gazi-irrigation.jpeg"
  },
  {
    "title": " TJSW-100 ECO গাজী পাম্প",
    "category": "WaterPump",
    "price": "৳ ৬৪৮৪",
    "des": "ফ্রিকোয়েন্সি: 50Hz পাম্প সাইড: কাস্ট আয়রন পাম্প বডি এবং ব্র্যাকেট। ব্রাশ আইএম-পেলার; স্টেইনলেস স্টীল খাদ; উচ্চ মানের যান্ত্রিক সীল. মান নিয়ন্ত্রণ: আমাদের সমস্ত পাম্প UNI 6871-71P Cat AII স্ট্যান্ডার্স অনুযায়ী পৃথকভাবে কারখানায় পরীক্ষা করা হয়। রঙ: দেওয়া ছবি হিসাবে",
    "picture": "https://images.othoba.com/images/thumbs/0487355_tjsw-100-eco-gazi-pump.jpeg"
  },
  {
    "title": " গাজী এয়ার কম্প্রেসার 2 H. P. ",
    "category": "WaterPump",
    "price": "৳ ১৫,৬৭৫",
    "des": "অগ্রিম অর্থ প্রদানের প্রয়োজনীয়তা: ঢাকা শহরের ভিতরে 100% COD ঢাকার বাইরে COD এর জন্য 10% অগ্রিম প্রয়োজন",
    "picture": "https://images.othoba.com/images/thumbs/0487311_gazi-air-compressor-2-h-p.jpeg"
  },
  {
    "title": "আরএফএল পিপি-আর প্লাস্টিক ইউনিয়ন",
    "category": "Pipes",
    "price": "৳ ৪৫৮",
    "des": "স্বয়ংক্রিয় থ্রেড কাটা খাদ্য গ্রেডেড কাঁচামাল",
    "picture": "https://images.othoba.com/images/thumbs/0362313_rfl-pp-r-plastic-union-50mm-1.jpeg"
  },
  {
    "title": " আরএফএল পিপি-আর ফিমেল থ্রেড টি ",
    "category": "Pipes",
    "price": "৳ ৩৯৭",
    "des": " স্বয়ংক্রিয় থ্রেড কাটা খাদ্য গ্রেডেড কাঁচামাল",
    "picture": "https://images.othoba.com/images/thumbs/0362217_rfl-pp-r-female-thread-tee-50mm-x-1.jpeg"
  },
  {
    "title": " আরএফএল পিপি-আর গেট ভালভ ",
    "category": "Pipes",
    "price": "৳ ১২৮২",
    "des": "আরএফএল PP-R গেট ভালভ 63mm ব্র্যান্ড  আরএফএল পিপিআর পাইপ এবং ফিটিংস আইটেম কোড ৯৮৯৩৬ আকার: ৬৩ মিমি ইউনিট: ১ টুকরারঙ: সবুজ প্রদত্ত ছবি হিসাবে",
    "picture": " https://images.othoba.com/images/thumbs/0362238_rfl-pp-r-gate-valve-63mm-2.jpeg"
  },
  {
    "title": " সাপোর্ট টেফন ট্যাপ ",
    "category": "Pipes",
    "price": "৳ ২০",
    "des": " ব্র্যান্ড: সাপোর্ট টেফলন টেপ আইটেম কোড: 700565 প্রকার: টেপের আকার: ১২মি x ১২ এমটি আর অ্যাপ্লিকেশন: জল, বায়ু বা গ্যাস লাইনের জন্য আদর্শ নিখুঁত দৈর্ঘ্য জলরোধী রঙ: সাদা (ছবি অনুযায়ী)।",
    "picture": "https://images.othoba.com/images/thumbs/0215180_support-taflon-tape-12mm-x-12-mtr-1-pc_400.jpeg"
  },
  {
    "title": " আরএফএল পিভিসি গার্ডেন হোস পাইপ ",
    "category": "Pipes",
    "price": "৳ ৪৫",
    "des": " অনেক শক্তিশালী. উন্নত প্রবাহ বৈশিষ্ট্য; জারা এবং রাসায়নিক প্রতিরোধী. নমনীয় এবং হালকা ওজন",
    "picture": "https://images.othoba.com/images/thumbs/0422198_rfl-pvc-garden-hose-pipe-2-orange-300_400.jpeg"
  },
  {
    "title": " ভিগো ওয়্যার গার্ড পাইপ ",
    "category": "Pipes",
    "price": "৳ ৯৫",
    "des": " ভিগো ওয়্যার গার্ড পাইপ ৩/৪ X ১০' কালো আইটেম কোড: ৯৮৪৯৩ ব্র্যান্ড: ভিগো ইলেকট্রিক পাইপ এবং ফিটিংস উপাদান: প্লাস্টিক পণ্যের ধরন: ওয়্যার গার্ড পাইপ বেধ:১.৫০-১.৭০ একক: টুকরা রঙ: কালো (প্রদত্ত ছবি হিসাবে)",
    "picture": "https://images.othoba.com/images/thumbs/0384225_vigo-wire-guard-pipe-34-x-10-black_400.jpeg"
  },
  {
    "title": "আনাহেইম মরিচের বীজ",
    "category": "Seeds",
    "price": "৳ ৬০",
    "des": "গুণমান চিলি মরিচ বীজ বীজ প্রয়োজন দ্বারা প্যাকেজ. বর্তমান এবং পরবর্তী ক্রমবর্ধমান ঋতু জন্য উদ্দেশ্যে.",
    "picture": "https://fixit.com.bd/wp-content/uploads/2021/06/863b1729-4c04-4d79-a5dd-a9d50d336b51_1-1.jpg"
  },
  {
    "title": "কলা মিষ্টি মরিচ বীজ",
    "category": "Seeds",
    "price": "৳ ১৬০",
    "des": "খামার এবং বাগান সবজি বীজ টেকসই বীজ কোম্পানি - পরিবারের মালিকানাধীন এবং পরিচালিত - প্রিমিয়াম গুণমান - নৈতিক এবং টেকসই বীজ।",
    "picture": "https://fixit.com.bd/wp-content/uploads/2021/06/71VBw5RFQ4L._AC_SL1500_-1.jpg"
  },
  {
    "title": "কালো তরমুজের বীজ",
    "category": "Seeds",
    "price": "৳ ২০৯",
    "des": "প্রকার:তরমুজের বীজ, আকৃতি:আয়তাকার, রঙ:কালো",
    "picture": "https://fixit.com.bd/wp-content/uploads/2021/06/black-watermelon-seeds-1.jpg"
  },
  {
    "title": "কুকুজ্জা করলা বীজ",
    "category": "Seeds",
    "price": "৳ ২০৮",
    "des": "বাংলাদেশে ভালো মানের Cucuzza Gourd বীজ পান টাইপসবজির বীজ সাধারণ নাম কুকুজ্জা করলা রঙ সবুজ",
    "picture": "https://fixit.com.bd/wp-content/uploads/2021/06/s-l640-1.jpg"
  },
  {
    "title": "সবুজ তিক্ত তরমুজের বীজ",
    "category": "Seeds",
    "price": "৳ ১৩৩",
    "des": "ডিশ স্যুপ জুস রান্নার জন্য আউটডোরে রোপণের জন্য উদ্ভিজ্জ জৈব সবুজ তাজা আরোহণ হার্ব বীজ: বাগান এবং আউটডোর",
    "picture": "https://fixit.com.bd/wp-content/uploads/2021/06/d8ca4b932fbd742088484c02e938a3bd-1.jpg"
  },

  {
    "title": "লাল মুলার বীজ",
    "category": "Seeds",
    "price": "৳ ৬০",
    "des": "৭০-৮0% অঙ্কুর ক্রাফট বীজ দ্বারা পরীক্ষিত এবং চমত্কার মানের দেখানো সমস্ত ছবি দৃষ্টান্তের উদ্দেশ্যে শুধুমাত্র প্রকৃত পণ্য পণ্য বর্ধনের কারণে পরিবর্তিত হতে পারে।",
    "picture": "https://fixit.com.bd/wp-content/uploads/2021/06/00664_01_rover-1.jpg"
  },
  {
    "title": "কালার লেপা তুয়া/রিজ",
    "category": "Tin",
    "price": "৳ ৮০/ফিট",
    "des": "ধেউ টিন/প্রোফাইল টিন, রিজ/তুয়া",
    "picture": "https://nirmanonline.com/wp-content/uploads/2021/12/color-coatet-plen-tua.jpg"
  },
  {
    "title": "অ্যালুমিনিয়াম এবং দস্তা লেপা",
    "category": "Tin",
    "price": "৳ ৬০/ফিট",
    "des": "ধেউ টিন/প্রোফাইল টিন, রিজ/তুয়া",
    "picture": "https://nirmanonline.com/wp-content/uploads/2021/12/Zinc-Ridge-Capping-Product.jpg"
  },
  {
    "title": "অ্যালুমিনিয়াম এবং দস্তা লেপা",
    "category": "Tin",
    "price": "৳ ৭০০/প্রতি",
    "des": "অ্যালুমিনিয়াম এবং দস্তা লেপা, ধেউ টিন/প্রোফাইল টিন",
    "picture": "https://nirmanonline.com/wp-content/uploads/2021/12/6-x-32-mm-aluminium-and-zinc-coated-600x392.jpg"
  },
  {
    "title": "নিয়মিত/নাফ টিন",
    "category": "Tin",
    "price": "৳ ৪৫০/প্রতি",
    "des": "ধেউ টিন/প্রোফাইল টিন, রেগুলার/নোফ",
    "picture": "https://nirmanonline.com/wp-content/uploads/2021/12/6-x-17-mm-Nof-600x600.jpg"
  },
  {
    "title": "রঙিন প্রলিপ্ত টিন",
    "category": "Tin",
    "price": "৳ ৫৫২/প্রতি",
    "des": "কালার কোটেড, ধেউ টিন/প্রোফাইল টিন",
    "picture": "https://nirmanonline.com/wp-content/uploads/2021/12/6-x-32-mm-Colour-Coated.jpg"
  },
  {
    "title": "শিল্প প্রোফাইল শীট",
    "category": "Tin",
    "price": "৳ ৭০০/প্রতি",
    "des": "ধেউ টিন/প্রোফাইল টিন, প্রোফাইল শীট",
    "picture": "https://nirmanonline.com/wp-content/uploads/2021/12/Industrial-Profile-Sheet-0.460-mm.jpg"
  }
]
